<Regions>
<Region><id>	1	</id><name>	Adilabad	</name></Region>
<Region><id>	2	</id><name>	A0tapur	</name></Region>
<Region><id>	3	</id><name>	Chittoor	</name></Region>
<Region><id>	4	</id><name>	Cuddapah	</name></Region>
<Region><id>	5	</id><name>	East Godavari	</name></Region>
<Region><id>	6	</id><name>	Guntur	</name></Region>
<Region><id>	7	</id><name>	Hyderabad	</name></Region>
<Region><id>	8	</id><name>	Karimnagar	</name></Region>
<Region><id>	9	</id><name>	Khammam	</name></Region>
<Region><id>	10	</id><name>	Krishna	</name></Region>
<Region><id>	11	</id><name>	Kurnool	</name></Region>
<Region><id>	12	</id><name>	Mahbubnagar	</name></Region>
<Region><id>	13	</id><name>	Medak	</name></Region>
<Region><id>	14	</id><name>	Nalgonda	</name></Region>
<Region><id>	15	</id><name>	Nellore	</name></Region>
<Region><id>	16	</id><name>	Nizamabad	</name></Region>
<Region><id>	17	</id><name>	Prakasam	</name></Region>
<Region><id>	18	</id><name>	Rangareddi	</name></Region>
<Region><id>	19	</id><name>	Srikakulam	</name></Region>
<Region><id>	20	</id><name>	Vishakhapatnam	</name></Region>
<Region><id>	21	</id><name>	Vizianagaram	</name></Region>
<Region><id>	22	</id><name>	Warangal	</name></Region>
<Region><id>	23	</id><name>	West Godavari	</name></Region>
</Regions>

